pureml_evaluate/__init__.py
pureml_evaluate/evaluators/__init__.py
pureml_evaluate/evaluators/config.json
pureml_evaluate/evaluators/description.json
pureml_evaluate/evaluators/evaluator.py
pureml_evaluate/evaluators/grade.py
pureml_evaluate/evaluators/graphs_generator.py
pureml_evaluate/evaluators/risk_evaluator.py
pureml_evaluate/evaluators/risk_evaluator_refactored.py
pureml_evaluate/evaluators/model/fairness/__init__.py
pureml_evaluate/evaluators/model/fairness/fairness.py
pureml_evaluate/evaluators/model/fairness/fairness_for_policy.py
pureml_evaluate/evaluators/model/performance/__init__.py
pureml_evaluate/evaluators/model/performance/classification.py
pureml_evaluate/evaluators/model/performance/nlp.py
pureml_evaluate/evaluators/model/performance/regression.py
pureml_evaluate/metrics/__init__.py
pureml_evaluate/metrics/metric_base.py
pureml_evaluate/metrics/readme.MD
pureml_evaluate/metrics/data/class_imbalance/class_imbalance.py
pureml_evaluate/metrics/data/data_bias/kullback_liebler_divergence.py
pureml_evaluate/metrics/data/data_drift/chi_squared_statistic/README.md
pureml_evaluate/metrics/data/data_drift/chi_squared_statistic/chi_squared_statistic.py
pureml_evaluate/metrics/data/data_drift/chi_squared_statistic/requirements.txt
pureml_evaluate/metrics/data/data_drift/cramers_v/README.md
pureml_evaluate/metrics/data/data_drift/cramers_v/cramers_v.py
pureml_evaluate/metrics/data/data_drift/cramers_v/requirements.txt
pureml_evaluate/metrics/data/data_drift/hellinger_distance/README.md
pureml_evaluate/metrics/data/data_drift/hellinger_distance/hellinger_distance.py
pureml_evaluate/metrics/data/data_drift/hellinger_distance/requirements.txt
pureml_evaluate/metrics/data/data_drift/kolmogorov_smirnov/README.md
pureml_evaluate/metrics/data/data_drift/kolmogorov_smirnov/kolmogorov_smirnov_statistic.py
pureml_evaluate/metrics/data/data_drift/kolmogorov_smirnov/requirements.txt
pureml_evaluate/metrics/data/data_drift/l_infinity_distance/README.md
pureml_evaluate-0.1.8.dist-info/METADATA
pureml_evaluate-0.1.8.dist-info/WHEEL
pureml_evaluate-0.1.8.dist-info/RECORD
